pywrapfst.so
openfst-1.6.9.dist-info/METADATA
openfst-1.6.9.dist-info/RECORD
openfst-1.6.9.dist-info/WHEEL
openfst-1.6.9.dist-info/top_level.txt
