Metadata-Version: 2.1
Name: openfst
Version: 1.6.9
Summary: Python wrapper for OpenFst
Home-page: http://python.openfst.org/
Author: Kyle Gorman
Author-email: kbg@google.com
License: UNKNOWN
Keywords: natural language processing,speech recognition,machine learning
Platform: UNKNOWN
Classifier: Programming Language :: Python :: 2.7
Classifier: Development Status :: 5 - Production/Stable
Classifier: Environment :: Other Environment
Classifier: Environment :: Console
Classifier: Intended Audience :: Developers
Classifier: License :: OSI Approved :: Apache Software License
Classifier: Operating System :: OS Independent
Classifier: Topic :: Software Development :: Libraries :: Python Modules
Classifier: Topic :: Text Processing :: Linguistic
Classifier: Topic :: Text Processing :: Filters
Classifier: Topic :: Text Processing :: General
Classifier: Topic :: Text Processing :: Indexing
Classifier: Topic :: Scientific/Engineering :: Mathematics
Classifier: Topic :: Scientific/Engineering :: Artificial Intelligence
